odiff/__init__.py
odiff/__main__.py
odiff/cli.py
odiff/discrepancy.py
odiff/logger.py
odiff/main.py
odiff/odiff.py
odiff/options.py
odiff/util.py
odiff-0.1.8.dist-info/METADATA
odiff-0.1.8.dist-info/WHEEL
odiff-0.1.8.dist-info/entry_points.txt
odiff-0.1.8.dist-info/RECORD
