Metadata-Version: 2.1
Name: odiff
Version: 0.1.8
Summary: 
Author: BodneyC
Author-email: benjcarrington@gmail.com
Requires-Python: >=3.11,<4.0
Classifier: Programming Language :: Python :: 3
Classifier: Programming Language :: Python :: 3.11
Classifier: Programming Language :: Python :: 3.12
Requires-Dist: colorlog (>=6.8.2,<7.0.0)
Requires-Dist: dacite (>=1.8.1,<2.0.0)
Requires-Dist: pyyaml (>=6.0.1,<7.0.0)
Requires-Dist: requests (>=2.31.0,<3.0.0)
Requires-Dist: tabulate (>=0.9.0,<0.10.0)
